hiero_did_sdk_python/__init__.py
hiero_did_sdk_python/anoncreds/__init__.py
hiero_did_sdk_python/anoncreds/hedera_anoncreds_registry.py
hiero_did_sdk_python/anoncreds/models/__init__.py
hiero_did_sdk_python/anoncreds/models/credential_definition.py
hiero_did_sdk_python/anoncreds/models/revocation/__init__.py
hiero_did_sdk_python/anoncreds/models/revocation/revocation_list.py
hiero_did_sdk_python/anoncreds/models/revocation/revocation_registry_definition.py
hiero_did_sdk_python/anoncreds/models/revocation/revocation_registry_entry.py
hiero_did_sdk_python/anoncreds/models/schema.py
hiero_did_sdk_python/anoncreds/types.py
hiero_did_sdk_python/anoncreds/utils.py
hiero_did_sdk_python/did/__init__.py
hiero_did_sdk_python/did/did_document.py
hiero_did_sdk_python/did/did_document_operation.py
hiero_did_sdk_python/did/did_error.py
hiero_did_sdk_python/did/did_syntax.py
hiero_did_sdk_python/did/hcs/__init__.py
hiero_did_sdk_python/did/hcs/events/__init__.py
hiero_did_sdk_python/did/hcs/events/document/__init__.py
hiero_did_sdk_python/did/hcs/events/document/hcs_did_create_did_document_event.py
hiero_did_sdk_python/did/hcs/events/document/hcs_did_delete_event.py
hiero_did_sdk_python/did/hcs/events/hcs_did_event.py
hiero_did_sdk_python/did/hcs/events/hcs_did_event_target.py
hiero_did_sdk_python/did/hcs/events/owner/__init__.py
hiero_did_sdk_python/did/hcs/events/owner/hcs_did_update_did_owner_event.py
hiero_did_sdk_python/did/hcs/events/service/__init__.py
hiero_did_sdk_python/did/hcs/events/service/hcs_did_revoke_service_event.py
hiero_did_sdk_python/did/hcs/events/service/hcs_did_update_service_event.py
hiero_did_sdk_python/did/hcs/events/verification_method/__init__.py
hiero_did_sdk_python/did/hcs/events/verification_method/hcs_did_revoke_verification_method_event.py
hiero_did_sdk_python/did/hcs/events/verification_method/hcs_did_update_verification_method_event.py
hiero_did_sdk_python/did/hcs/events/verification_relationship/__init__.py
hiero_did_sdk_python-0.1.1.dist-info/LICENSE
hiero_did_sdk_python-0.1.1.dist-info/METADATA
hiero_did_sdk_python-0.1.1.dist-info/WHEEL
hiero_did_sdk_python-0.1.1.dist-info/RECORD
