Metadata-Version: 2.1
Name: hiero-did-sdk-python
Version: 0.1.1
Summary: The repository contains the Python SDK for managing DID Documents and Anoncreds Verifiable Credentials registry using Hedera Consensus Service.
Home-page: https://github.com/hiero-ledger/hiero-did-sdk-python
Author: Alexander Shenshin
Author-email: alexander.shenshin@dsr-corporation.com
Requires-Python: >=3.12,<4.0
Classifier: Programming Language :: Python :: 3
Classifier: Programming Language :: Python :: 3.12
Classifier: Programming Language :: Python :: 3.13
Requires-Dist: aiohttp (>=3.10.9,<4.0.0)
Requires-Dist: aiohttp_retry (>=2.9.0,<3.0.0)
Requires-Dist: base58 (>=2.1.1,<3.0.0)
Requires-Dist: did-resolver (==0.0.3)
Requires-Dist: hiero_sdk_python (==0.1.6)
Requires-Dist: zstandard (>=0.23.0,<0.24.0)
Project-URL: Documentation, https://hiero-ledger.github.io/hiero-did-sdk-python/
Project-URL: Repository, https://github.com/hiero-ledger/hiero-did-sdk-python
